{
  "book": "PSA",
  "rev": "TLA",
  "chapter": "26",
  "verses": [
    {
      "verse": "1",
      "text": "26 1-2 Dios mío,\ndeclárame inocente,\npues vivo una vida honrada\ny en ti confío ciegamente.\nDime si te agrada\nlo que pienso y lo que siento.",
      "readableText": "26 1-2 Dios mío, declárame inocente, pues vivo una vida honrada y en ti confío ciegamente. Dime si te agrada lo que pienso y lo que siento."
    },
    {
      "verse": "2",
      "text": "",
      "readableText": ""
    },
    {
      "verse": "3",
      "text": "Yo siempre recuerdo tu amor\ny por eso te soy fiel. 4-5 No me junto con gente tramposa\nni ando con gente mala y perversa.\n¡No soporto cerca de mí\na gente que no es sincera!",
      "readableText": "Yo siempre recuerdo tu amor y por eso te soy fiel. 4-5 No me junto con gente tramposa ni ando con gente mala y perversa. ¡No soporto cerca de mí a gente que no es sincera!"
    },
    {
      "verse": "4",
      "text": "",
      "readableText": ""
    },
    {
      "verse": "5",
      "text": "",
      "readableText": ""
    },
    {
      "verse": "6",
      "text": "Dios mío,\nyo no he hecho nada malo;\npor eso me acerco a tu altar",
      "readableText": "Dios mío, yo no he hecho nada malo; por eso me acerco a tu altar"
    },
    {
      "verse": "7",
      "text": "para cantarte a voz en cuello\nmis himnos de alabanza\ny hablar de tus grandes hechos.",
      "readableText": "para cantarte a voz en cuello mis himnos de alabanza y hablar de tus grandes hechos."
    },
    {
      "verse": "8",
      "text": "Dios mío,\nyo amo el templo donde vives,\ndonde se hace presente tu grandeza.",
      "readableText": "Dios mío, yo amo el templo donde vives, donde se hace presente tu grandeza."
    },
    {
      "verse": "9",
      "text": "No me dejes morir\nentre gente pecadora;\nno me quites la vida\njunto con gente asesina,",
      "readableText": "No me dejes morir entre gente pecadora; no me quites la vida junto con gente asesina,"
    },
    {
      "verse": "10",
      "text": "gente que tiene en sus manos\nel dinero que ha ganado con engaños. 11-12 Dios mío,\nyo quiero seguir siendo honrado;\nten compasión de mí, y sálvame.\nAsí me mantendré fiel a ti,\ny con todo tu pueblo te alabaré.",
      "readableText": "gente que tiene en sus manos el dinero que ha ganado con engaños. 11-12 Dios mío, yo quiero seguir siendo honrado; ten compasión de mí, y sálvame. Así me mantendré fiel a ti, y con todo tu pueblo te alabaré."
    }
  ]
}