{
  "book": "PSA",
  "rev": "TLA",
  "chapter": "123",
  "verses": [
    {
      "verse": "1",
      "text": "123 1-2 Dios, rey de los cielos,\nde ti dependemos,\ncomo dependen los esclavos\nde la compasión de sus amos.Dios nuestro,\nde ti dependemos y esperamos\nque nos tengas compasión.\n3-4 ¡Compadécete de nosotros!\n¡Ya estamos cansados\nde que esos ricos orgullosos\nnos ofendan y nos desprecien!",
      "readableText": "123 1-2 Dios, rey de los cielos, de ti dependemos, como dependen los esclavos de la compasión de sus amos.Dios nuestro, de ti dependemos y esperamos que nos tengas compasión. 3-4 ¡Compadécete de nosotros! ¡Ya estamos cansados de que esos ricos orgullosos nos ofendan y nos desprecien!"
    }
  ]
}