{"book":"PSA","rev":"RVR60","chapter":"111","verses":[{"verse":"1","text":"Alabar&#233; a Jehov&#225; con todo el coraz&#243;n En la compa&#241;&#237;a y congregaci&#243;n de los rectos.   \n","readableText":"Alabaré a Jehová con todo el corazón En la compañía y congregación de los\nrectos.\n\n"},{"verse":"2","text":"Grandes son las obras de Jehov&#225;, Buscadas de todos los que las quieren.   \n","readableText":"Grandes son las obras de Jehová, Buscadas de todos los que las quieren.\n\n"},{"verse":"3","text":"Gloria y hermosura es su obra, Y su justicia permanece para siempre.   \n","readableText":"Gloria y hermosura es su obra, Y su justicia permanece para siempre.\n\n"},{"verse":"4","text":"Ha hecho memorables sus maravillas; Clemente y misericordioso es Jehov&#225;.   \n","readableText":"Ha hecho memorables sus maravillas; Clemente y misericordioso es Jehová.\n\n"},{"verse":"5","text":"Ha dado alimento a los que le temen; Para siempre se acordar&#225; de su pacto.   \n","readableText":"Ha dado alimento a los que le temen; Para siempre se acordará de su pacto.\n\n"},{"verse":"6","text":"El poder de sus obras manifest&#243; a su pueblo, D&#225;ndole la heredad de las naciones.   \n","readableText":"El poder de sus obras manifestó a su pueblo, Dándole la heredad de las\nnaciones.\n\n"},{"verse":"7","text":"Las obras de sus manos son verdad y juicio; Fieles son todos sus mandamientos,   \n","readableText":"Las obras de sus manos son verdad y juicio; Fieles son todos sus mandamientos,\n\n\n"},{"verse":"8","text":"Afirmados eternamente y para siempre, Hechos en verdad y en rectitud.   \n","readableText":"Afirmados eternamente y para siempre, Hechos en verdad y en rectitud.\n\n"},{"verse":"9","text":"Redenci&#243;n ha enviado a su pueblo; Para siempre ha ordenado su pacto; Santo y temible es su nombre.   \n","readableText":"Redención ha enviado a su pueblo; Para siempre ha ordenado su pacto; Santo y\ntemible es su nombre.\n\n"},{"verse":"10","text":"El principio de la sabidur&#237;a es el temor de Jehov&#225;; Buen entendimiento tienen todos los que practican sus mandamientos; Su loor permanece para siempre.\n","readableText":"El principio de la sabiduría es el temor de Jehová; Buen entendimiento tienen\ntodos los que practican sus mandamientos; Su loor permanece para siempre.\n\n"}]}
